LICENSE
MANIFEST.in
README.md
README.rst
setup.py
methplotlib/__init__.py
methplotlib/annotation.py
methplotlib/helpers.py
methplotlib/import_methylation.py
methplotlib/methplotlib.py
methplotlib/plots.py
methplotlib/qc.py
methplotlib/utils.py
methplotlib/version.py
methplotlib.egg-info/PKG-INFO
methplotlib.egg-info/SOURCES.txt
methplotlib.egg-info/dependency_links.txt
methplotlib.egg-info/entry_points.txt
methplotlib.egg-info/requires.txt
methplotlib.egg-info/top_level.txt
methplotlib/differential/__init__.py
methplotlib/differential/differential.py
scripts/__init__.py
scripts/allele_specific_modification
scripts/annotate_calls_by_phase.py
scripts/calculate_methylation_frequency.py
scripts/differential_modification
scripts/genome-wide-QC.py
scripts/sorting_and_multiple_testing_correction.py
scripts/split_calls_by_longshot_phase.py
scripts/split_calls_by_phase.py