Metadata-Version: 2.1
Name: methplotlib
Version: 0.21.2
Summary: Plot methylation data obtained from nanopolish
Home-page: https://github.com/wdecoster/methplotlib
Author: Wouter De Coster
Author-email: decosterwouter@gmail.com
License: MIT
Keywords: nanopore
Classifier: Development Status :: 4 - Beta
Classifier: Intended Audience :: Science/Research
Classifier: Topic :: Scientific/Engineering :: Bio-Informatics
Classifier: License :: OSI Approved :: MIT License
Classifier: Programming Language :: Python :: 3
Classifier: Programming Language :: Python :: 3.3
Classifier: Programming Language :: Python :: 3.4
Classifier: Programming Language :: Python :: 3.5
Requires-Python: >=3
License-File: LICENSE
